awesomeff2/__init__.py
awesomeff2/bin/__init__.py
awesomeff2/bin/ffmpeg
awesomeff2/bin/ffprobe
awesomeff2-0.1.0.dist-info/METADATA
awesomeff2-0.1.0.dist-info/WHEEL
awesomeff2-0.1.0.dist-info/top_level.txt
awesomeff2-0.1.0.dist-info/RECORD
