Metadata-Version: 2.4
Name: awesomeff2
Version: 0.1.0
Summary: wraps FFMPEG. see FFMPEG license
Dynamic: summary
